{
  "task": "feat: servidor headless (HTTP/SSE) para integração com CI/CD e clientes externos (issue #49)",
  "todos": [
    {
      "id": "1",
      "title": "Add Headless config fields (Enabled, Host, Port) to Config struct and TomlConfig — supports devon.toml [headless] section",
      "files": [
        "internal/config/config.go",
        "internal/config/profiles.go"
      ],
      "done": true,
      "dep": "-"
    },
    {
      "id": "2",
      "title": "Add --headless, --port, --host persistent flags to root cobra command and create headless subcommand skeleton",
      "files": [
        "cmd/devon/main.go"
      ],
      "done": true,
      "dep": "1"
    },
    {
      "id": "3",
      "title": "Create proto/devon.proto — reference gRPC service definition with DevonService, event types (text_delta, tool_start, tool_done, action_required, turn_done, error), and bidirectional streaming RPC",
      "files": [
        "proto/devon.proto"
      ],
      "done": true,
      "dep": "-"
    },
    {
      "id": "4",
      "title": "Create internal/headless/types.go — public API types: PromptRequest, EventResponse (type + payload), ActionRequiredRequest, RespondRequest, SSE event constants, reusable Event type aliases",
      "files": [
        "internal/headless/types.go"
      ],
      "done": true,
      "dep": "1"
    },
    {
      "id": "5",
      "title": "Create internal/headless/server.go — HTTP server struct with Listen/Serve/Close, SSE connection manager (per-client event queue, graceful close), integrates with agent.ReplyCh for action_required blocking",
      "files": [
        "internal/headless/server.go"
      ],
      "done": true,
      "dep": "4"
    },
    {
      "id": "6",
      "title": "Create internal/headless/handler.go — HTTP handlers: POST /api/prompt (accepts prompt → returns SSE stream), POST /api/respond (unblocks action_required), GET /api/health, GET /api/status. Maps agent.Event types to SSE events, handles confirm_request → action_required flow",
      "files": [
        "internal/headless/handler.go"
      ],
      "done": true,
      "dep": "5"
    },
    {
      "id": "7",
      "title": "Create internal/headless/server_test.go — tests with mock agent: SSE stream receives text_delta/tool_start/tool_done/turn_done, action_required blocks until /api/respond, health endpoint returns 200, concurrent clients",
      "files": [
        "internal/headless/server_test.go"
      ],
      "done": true,
      "dep": "6"
    },
    {
      "id": "8",
      "title": "Implement runHeadless function in cmd/devon/main.go — init agent, create headless server, wire agent events to SSE stream, handle action_required via HTTP endpoint, serve until SIGINT. Wire into --headless flag and headless subcommand",
      "files": [
        "cmd/devon/main.go"
      ],
      "done": true,
      "dep": "2,6"
    },
    {
      "id": "9",
      "title": "Add [headless] sample config section to devon.toml — host, port, enabled fields with documentation comments",
      "files": [
        "devon.toml"
      ],
      "done": true,
      "dep": "1"
    },
    {
      "id": "10",
      "title": "Verify build, lint, and tests pass — go build ./..., go test ./..., go vet ./..., golangci-lint run across all packages",
      "files": [
        "internal/headless/server.go",
        "internal/headless/handler.go",
        "internal/headless/types.go",
        "internal/headless/server_test.go",
        "cmd/devon/main.go",
        "internal/config/config.go",
        "internal/config/profiles.go",
        "proto/devon.proto",
        "devon.toml"
      ],
      "done": true,
      "dep": "3,7,8,9"
    }
  ]
}
